pygraphgpt/controller/app.py
pygraphgpt/controller/configs/style.json
pygraphgpt/controller/constants.py
pygraphgpt/domain/graph.py
pygraphgpt/domain/utils.py
pygraphgpt-0.1.1.dist-info/LICENSE
pygraphgpt-0.1.1.dist-info/METADATA
pygraphgpt-0.1.1.dist-info/WHEEL
pygraphgpt-0.1.1.dist-info/entry_points.txt
pygraphgpt-0.1.1.dist-info/RECORD
