Metadata-Version: 2.1
Name: pygraphgpt
Version: 0.1.1
Summary: 
Author: An Truong
Author-email: antruong.bq@gmail.com
Requires-Python: >=3.9,<4
Classifier: Programming Language :: Python :: 3
Classifier: Programming Language :: Python :: 3.9
Classifier: Programming Language :: Python :: 3.10
Classifier: Programming Language :: Python :: 3.11
Requires-Dist: chardet (>=5.2.0,<6.0.0)
Requires-Dist: charset-normalizer (==2.1.0)
Requires-Dist: dash (>=2.13.0,<3.0.0)
Requires-Dist: dash-bootstrap-components (>=1.5.0,<2.0.0)
Requires-Dist: dash-core-components (>=2.0.0,<3.0.0)
Requires-Dist: dash-cytoscape (>=0.3.0,<0.4.0)
Requires-Dist: dash-html-components (>=2.0.0,<3.0.0)
Requires-Dist: dash-table (>=5.0.0,<6.0.0)
Requires-Dist: openai (>=0.27.8,<0.28.0)
Requires-Dist: pandas (>=2.1.0,<3.0.0)
Requires-Dist: poetry (>=1.6.1,<2.0.0)
Requires-Dist: python-dotenv (>=0.21.0,<0.22.0)
